lint4jira/__init__.py
lint4jira/__main__.py
lint4jira/bcolors.py
lint4jira/jiralint.py
lint4jira/jirapi.py
lint4jira/selector.py
lint4jira-0.21.dist-info/METADATA
lint4jira-0.21.dist-info/WHEEL
lint4jira-0.21.dist-info/entry_points.txt
lint4jira-0.21.dist-info/top_level.txt
lint4jira-0.21.dist-info/RECORD
