Metadata-Version: 2.1
Name: lint4jira
Version: 0.21
Summary: lint4jira is a calculator for Jira tasks or sprints health. It calculates the health of the tasks in a sprint or a single task in Jira.
Home-page: https://github.com/alameddinc/lint4jira
Author: Alameddin Çelik
Author-email: alameddinc@gmail.com
License: MIT
Keywords: jira health sprint task
Platform: UNKNOWN
Requires-Dist: jira
Requires-Dist: requests
Requires-Dist: argparse
Requires-Dist: windows-curses ; platform_system == "Windows"
